playbook3d/__init__.py
playbook3d/playbookErrorHandler.py
playbook3d/playbookNetworkClient.py
playbook3d/playbookPrivateModel.py
playbook3d/playbookRun.py
playbook3d/playbookTeam.py
playbook3d/playbookUser.py
playbook3d/playbookWorkflow.py
playbook3d-0.0.1.dist-info/METADATA
playbook3d-0.0.1.dist-info/WHEEL
playbook3d-0.0.1.dist-info/licenses/LICENSE
playbook3d-0.0.1.dist-info/RECORD
